LICENCE.rst
MANIFEST.in
README.rst
setup.py
src/Products/__init__.py
src/Products.MxDateTimeField.egg-info/PKG-INFO
src/Products.MxDateTimeField.egg-info/SOURCES.txt
src/Products.MxDateTimeField.egg-info/dependency_links.txt
src/Products.MxDateTimeField.egg-info/entry_points.txt
src/Products.MxDateTimeField.egg-info/namespace_packages.txt
src/Products.MxDateTimeField.egg-info/not-zip-safe
src/Products.MxDateTimeField.egg-info/requires.txt
src/Products.MxDateTimeField.egg-info/top_level.txt
src/Products/MxDateTimeField/MxDateTimeField.py
src/Products/MxDateTimeField/MxDateTimeWidget.py
src/Products/MxDateTimeField/__init__.py
src/Products/MxDateTimeField/configure.zcml
src/Products/MxDateTimeField/mxdateindex/MxDateIndex.py
src/Products/MxDateTimeField/mxdateindex/__init__.py
src/Products/MxDateTimeField/mxdateindex/dtml/addMxDateIndex.dtml
src/Products/MxDateTimeField/mxdateindex/dtml/browseMxIndex.dtml
src/Products/MxDateTimeField/mxdateindex/dtml/manageMxDateIndex.dtml
src/Products/MxDateTimeField/mxdaterangeindex/MxDateRangeIndex.py
src/Products/MxDateTimeField/mxdaterangeindex/__init__.py
src/Products/MxDateTimeField/mxdaterangeindex/dtml/addMxDateRangeIndex.dtml
src/Products/MxDateTimeField/mxdaterangeindex/dtml/manageMxDateRangeIndex.dtml
src/Products/MxDateTimeField/profiles/default/metadata.xml
src/Products/MxDateTimeField/profiles/default/skins.xml
src/Products/MxDateTimeField/skins/MxDateTimeField/MxDateTimeWidget.pt
src/Products/MxDateTimeField/www/index.gif