Metadata-Version: 1.1
Name: Products.MxDateTimeField
Version: 1.2
Summary: Archetypes Field using MxDateTime
Home-page: https://pypi.python.org/pypi/Products.MxDateTimeField
Author: BlueDynamics Alliance
Author-email: dev@bluedynamics.com
License: GPLv2
Platform: UNKNOWN
Classifier: Development Status :: 5 - Production/Stable
Classifier: License :: OSI Approved :: GNU General Public License (GPL)
Classifier: Operating System :: OS Independent
Classifier: Programming Language :: Python
Classifier: Topic :: Software Development
Classifier: Framework :: Plone
